pyphenopop/__init__.py
pyphenopop/mixpopid.py
pyphenopop/plotting.py
pyphenopop-0.0.2.dist-info/LICENSE
pyphenopop-0.0.2.dist-info/METADATA
pyphenopop-0.0.2.dist-info/WHEEL
pyphenopop-0.0.2.dist-info/top_level.txt
pyphenopop-0.0.2.dist-info/RECORD
