Metadata-Version: 2.1
Name: pyphenopop
Version: 0.0.2
Summary: Phenotypic deconvolution in heterogeneous cancer cell populations using drug screen data
Home-page: https://github.com/ocbe-uio/pyPhenoPop
Author: Leonard Schmiester, Polina Arsenteva, Even Myklebust, Alvaro Köhn-Luque
Author-email: leonargs@uio.no, apolinaria10@mail.ru, e.m.myklebust@medisin.uio.no, a.k.luque@medisin.uio.no
License: MIT
Classifier: License :: OSI Approved :: MIT License
Classifier: Programming Language :: Python
Classifier: Programming Language :: Python :: 3
Classifier: Programming Language :: Python :: 3.8
Classifier: Programming Language :: Python :: 3.9
Classifier: Programming Language :: Python :: 3.10
Classifier: Operating System :: OS Independent
Requires-Python: >=3.8.0
License-File: LICENSE
Requires-Dist: matplotlib ==3.5.3
Requires-Dist: scipy >=1.9.3
Requires-Dist: numpy >=1.23.4
Requires-Dist: pandas >=1.5.1
Requires-Dist: tqdm >=4.64.1
